.gitignore
.pre-commit-config.yaml
LICENSE
README.rst
bitbucket-pipelines.yml
pyproject.toml
setup.cfg
setup.py
logging42/__init__.py
logging42/configuration_logger.py
logging42/logger.py
logging42.egg-info/PKG-INFO
logging42.egg-info/SOURCES.txt
logging42.egg-info/dependency_links.txt
logging42.egg-info/requires.txt
logging42.egg-info/top_level.txt
logging42/tests/__init__.py
logging42/tests/test_configuration_logger.py