Metadata-Version: 2.1
Name: logging42
Version: 0.0.8
Summary: A configuration of the loguru logger
Home-page: https://bitbucket.org/dkistdc/logging_config/src/master/
Author: NSO / AURA
Author-email: "swiant@nso.edu"
License: MIT
Platform: UNKNOWN
Classifier: Programming Language :: Python
Classifier: Programming Language :: Python :: 3
Classifier: Programming Language :: Python :: 3.7
Requires-Python: >=3.7
Provides-Extra: test
License-File: LICENSE
